LICENSE.txt
MANIFEST.in
README.md
setup.cfg
setup.py
test.py
blueapps/__init__.py
blueapps/account/__init__.py
blueapps/account/admin.py
blueapps/account/apps.py
blueapps/account/backends.py
blueapps/account/conf.py
blueapps/account/decorators.py
blueapps/account/forms.py
blueapps/account/middlewares.py
blueapps/account/models.py
blueapps/account/readme.md
blueapps/account/urls.py
blueapps/account/views.py
blueapps/account/components/__init__.py
blueapps/account/components/bk_jwt/__init__.py
blueapps/account/components/bk_jwt/backends.py
blueapps/account/components/bk_jwt/middlewares.py
blueapps/account/components/bk_token/__init__.py
blueapps/account/components/bk_token/backends.py
blueapps/account/components/bk_token/forms.py
blueapps/account/components/bk_token/middlewares.py
blueapps/account/components/bk_token/models.py
blueapps/account/components/null/__init__.py
blueapps/account/components/weixin/__init__.py
blueapps/account/components/weixin/backends.py
blueapps/account/components/weixin/forms.py
blueapps/account/components/weixin/middlewares.py
blueapps/account/handlers/__init__.py
blueapps/account/handlers/response.py
blueapps/account/management/__init__.py
blueapps/account/management/commands/__init__.py
blueapps/account/management/commands/apigw_clean_cache.py
blueapps/account/migrations/0001_initial.py
blueapps/account/migrations/0002_init_superuser.py
blueapps/account/migrations/0003_verifyinfo.py
blueapps/account/migrations/0004_create_cache_table.py
blueapps/account/migrations/__init__.py
blueapps/account/sites/__init__.py
blueapps/account/sites/default.py
blueapps/account/sites/open/__init__.py
blueapps/account/sites/open/conf.py
blueapps/account/static/account/login.js
blueapps/account/templates/account/login_page.html
blueapps/account/templates/account/login_success.html
blueapps/account/utils/__init__.py
blueapps/account/utils/http.py
blueapps/account/utils/sms.py
blueapps/conf/__init__.py
blueapps/conf/database.py
blueapps_open.egg-info/PKG-INFO
blueapps_open.egg-info/SOURCES.txt
blueapps_open.egg-info/dependency_links.txt
blueapps_open.egg-info/entry_points.txt
blueapps_open.egg-info/not-zip-safe
blueapps_open.egg-info/requires.txt
blueapps_open.egg-info/top_level.txt