Metadata-Version: 2.1
Name: blueapps-open
Version: 3.5.3
Summary: development framework for blueking
Home-page: https://github.com/TencentBlueKing/blueapps
Author: blueking
Author-email: blueking@tencent.com
License: UNKNOWN
Platform: UNKNOWN
Provides-Extra: opentelemetry
